pyhill/__init__.py
pyhill-0.0.3.dist-info/LICENSE
pyhill-0.0.3.dist-info/METADATA
pyhill-0.0.3.dist-info/WHEEL
pyhill-0.0.3.dist-info/top_level.txt
pyhill-0.0.3.dist-info/RECORD
