Metadata-Version: 2.1
Name: pyhill
Version: 0.0.3
Summary: Easily modify the readwritememory of Brick Hill.
Home-page: https://github.com/Yekc/PyHill/tree/main
Author: Yek
Author-email: gwojtysiak34@gmail.com
License: UNKNOWN
Platform: UNKNOWN
Classifier: Programming Language :: Python :: 3
Classifier: License :: OSI Approved :: MIT License
Classifier: Operating System :: OS Independent
Requires-Python: >=3.6
